./.gitignore
./PKG-INFO
./README.md
./pyproject.toml
./vision_agents/plugins/huggingface/__init__.py
./vision_agents/plugins/huggingface/events.py
./vision_agents/plugins/huggingface/huggingface_llm.py
./vision_agents/plugins/huggingface/huggingface_vlm.py
vision_agents_plugins_huggingface-0.2.10.dist-info/METADATA
vision_agents_plugins_huggingface-0.2.10.dist-info/WHEEL
vision_agents_plugins_huggingface-0.2.10.dist-info/RECORD
