Metadata-Version: 2.4
Name: vision-agents-plugins-huggingface
Version: 0.2.10
Summary: HuggingFace Inference integration for Vision Agents
Project-URL: Documentation, https://visionagents.ai/
Project-URL: Website, https://visionagents.ai/
Project-URL: Source, https://github.com/GetStream/Vision-Agents
License-Expression: MIT
Keywords: AI,LLM,agents,huggingface,inference,voice agents
Requires-Python: >=3.10
Requires-Dist: huggingface-hub<1.0
Requires-Dist: vision-agents
